.project
.pydevproject
README.txt
setup.cfg
setup.py
docs/HISTORY.txt
docs/INSTALL.txt
docs/LICENSE.GPL
docs/LICENSE.txt
operun/__init__.py
operun.linkportlet.egg-info/PKG-INFO
operun.linkportlet.egg-info/SOURCES.txt
operun.linkportlet.egg-info/dependency_links.txt
operun.linkportlet.egg-info/entry_points.txt
operun.linkportlet.egg-info/namespace_packages.txt
operun.linkportlet.egg-info/not-zip-safe
operun.linkportlet.egg-info/requires.txt
operun.linkportlet.egg-info/top_level.txt
operun/linkportlet/__init__.py
operun/linkportlet/config.py
operun/linkportlet/configure.zcml
operun/linkportlet/events.py
operun/linkportlet/interfaces.py
operun/linkportlet/tests.py
operun/linkportlet/browser/__init__.py
operun/linkportlet/browser/configure.zcml
operun/linkportlet/browser/link.pt
operun/linkportlet/browser/link.py
operun/linkportlet/content/__init__.py
operun/linkportlet/content/configure.zcml
operun/linkportlet/content/link.py
operun/linkportlet/content/linkarea.py
operun/linkportlet/content/linkfolder.py
operun/linkportlet/portlets/__init__.py
operun/linkportlet/portlets/configure.zcml
operun/linkportlet/portlets/linkportlet.pt
operun/linkportlet/portlets/linkportlet.py
operun/linkportlet/portlets/linkvocabulary.py
operun/linkportlet/profiles/default/catalog.xml
operun/linkportlet/profiles/default/factorytool.xml
operun/linkportlet/profiles/default/metadata.xml
operun/linkportlet/profiles/default/portlets.xml
operun/linkportlet/profiles/default/propertiestool.xml
operun/linkportlet/profiles/default/types.xml
operun/linkportlet/profiles/default/types/operun_Link.xml
operun/linkportlet/profiles/default/types/operun_Link_Area.xml
operun/linkportlet/profiles/default/types/operun_Link_Folder.xml