Metadata-Version: 1.0
Name: operun.linkportlet
Version: 1.1.5
Summary: Display Links selected from a Link collection inside a Portlet
Home-page: http://svn.operun.de/svn/operun.linkportlet
Author: Stefan Antonelli
Author-email: stefan.antonelli@operun.de
License: GPL
Keywords: Plone Portlet Links
Platform: UNKNOWN
Classifier: Framework :: Plone
Classifier: Programming Language :: Python
Classifier: Intended Audience :: End Users/Desktop
Classifier: Intended Audience :: System Administrators
Classifier: License :: OSI Approved :: GNU General Public License (GPL)
